figuratenum/FigurateNum.py
figuratenum/NumCollector.py
figuratenum/__init__.py
figuratenum/utils.py
figuratenum/figurate_viz/FigurateViz.py
figuratenum/figurate_viz/GaussianPlots.py
figuratenum/multidimensional_figurate_numbers/MultidimensionalFigurateNum.py
figuratenum/multidimensional_figurate_numbers/multidimensional_figuratenum.py
figuratenum/multidimensional_figurate_numbers/specific_multidimensional_figuratenum.py
figuratenum/plane_figurate_numbers/PlaneFigurateNum.py
figuratenum/plane_figurate_numbers/plane_figuratenum.py
figuratenum/plane_figurate_numbers/specific_plane_figuratenum.py
figuratenum/space_figurate_numbers/SpaceFigurateNum.py
figuratenum/space_figurate_numbers/space_figuratenum.py
figuratenum/space_figurate_numbers/specific_space_figuratenum.py
figuratenum/zoo_figurate_numbers/ZooFigurateNum.py
figuratenum/zoo_figurate_numbers/zoo_figuratenum.py
figuratenum-2.1.1.dist-info/licenses/LICENSE
figuratenum-2.1.1.dist-info/METADATA
figuratenum-2.1.1.dist-info/WHEEL
figuratenum-2.1.1.dist-info/top_level.txt
figuratenum-2.1.1.dist-info/RECORD
