Metadata-Version: 2.4
Name: figuratenum
Version: 2.1.1
Summary: Generate 235 infinite figurate number sequences across multiple dimensions for mathematical research, applications, and exploration in Python.
Author: Edgar Armando Delgado Vega
License-Expression: MIT
Project-URL: Homepage, https://github.com/edelveart/figuratenum
Project-URL: Source, https://github.com/edelveart/figuratenum
Keywords: generators,figurate numbers,infinite sequences,number sequences,number generators
Classifier: Programming Language :: Python :: 3
Classifier: Development Status :: 5 - Production/Stable
Classifier: Topic :: Scientific/Engineering :: Mathematics
Classifier: Topic :: Software Development :: Libraries :: Python Modules
Classifier: Intended Audience :: Developers
Classifier: Intended Audience :: Science/Research
Classifier: Intended Audience :: Education
Classifier: Operating System :: MacOS :: MacOS X
Classifier: Operating System :: Microsoft :: Windows
Classifier: Operating System :: POSIX :: Linux
Requires-Python: >=3.10
License-File: LICENSE
Provides-Extra: dev
Requires-Dist: autopep8; extra == "dev"
Requires-Dist: pytest; extra == "dev"
Provides-Extra: figurate-viz
Requires-Dist: matplotlib>=3.10.0; extra == "figurate-viz"
Requires-Dist: numpy>=2.2.2; extra == "figurate-viz"
Dynamic: license-file
